setup.py
xooof/__init__.py
xooof.xmlstruct.egg-info/PKG-INFO
xooof.xmlstruct.egg-info/SOURCES.txt
xooof.xmlstruct.egg-info/dependency_links.txt
xooof.xmlstruct.egg-info/entry_points.txt
xooof.xmlstruct.egg-info/namespace_packages.txt
xooof.xmlstruct.egg-info/not-zip-safe
xooof.xmlstruct.egg-info/requires.txt
xooof.xmlstruct.egg-info/top_level.txt
xooof/xmlstruct/__init__.py
xooof/xmlstruct/domutils.py
xooof/xmlstruct/errorbag.py
xooof/xmlstruct/handlers.py
xooof/xmlstruct/metafield.py
xooof/xmlstruct/translations.py
xooof/xmlstruct/typeinfo.py
xooof/xmlstruct/utils.py
xooof/xmlstruct/xmlstruct.py
xooof/xmlstruct/xsdatetime.py
xooof/xmlstruct/xsiso.py