Metadata-Version: 1.0
Name: xooof.xmlstruct
Version: 0.1
Summary: The xmlstruct part of the xooof runtime for python
Home-page: http://sourceforge.net/projects/xooof/
Author: xooof community
Author-email: Stephane Bidoul
License: GNU Lesser General Public License
Keywords: xooof xmlstruct xml serializable
Platform: UNKNOWN
Classifier: Programming Language :: Python
Classifier: Topic :: Software Development :: Libraries :: Python Modules
